Metadata-Version: 1.1
Name: browseapi-sandbox
Version: 0.5
Summary: eBay Browse API Python client
Home-page: https://github.com/atedrow/browseapi_sandbox
Author: Alexander Tedrow
Author-email: atedrow@clemson.edu
License: MIT
Download-URL: https://github.com/atedrow/browseapi_sandbox/archive/refs/tags/v_05.tar.gz
Keywords: ASYNC,BROWSE API,CLIENT
Platform: UNKNOWN
Classifier: Development Status :: 3 - Alpha
Classifier: Intended Audience :: Developers
Classifier: Topic :: Software Development :: Libraries
Classifier: License :: OSI Approved :: MIT License
Classifier: Programming Language :: Python :: 3.5
Classifier: Programming Language :: Python :: 3.6
Classifier: Programming Language :: Python :: 3.7
